Workbook

Sheet Loan EMI
A1: Loan EMI Calculator
A4: Loan amount | B4: 5000000
A5: Annual interest rate | B5: 0.085
A6: Tenure (years) | B6: 20
A8: Results
A9: Monthly interest rate | B9: =B5/12 -> 0.0070833333
A10: Number of months | B10: =B6*12 -> 240
A11: Monthly EMI | B11: =IFERROR(PMT(B9,B10,-B4),0) -> 43391.162
A12: Total payment | B12: =B11*B10 -> 10413879
A13: Total interest | B13: =B12-B4 -> 5413878.8
A14: Interest as % of loan | B14: =IFERROR(B13/B4,0) -> 1.0827758

Sheet Amortization
A1: Amortization Schedule (linked to Loan EMI sheet, up to 30 years)
A3: Month | B3: Opening balance | C3: EMI | D3: Interest | E3: Principal | F3: Closing balance
A4: =IF(1<='Loan EMI'!$B$10,1,"") -> 1 | B4: =IF(A4="","",'Loan EMI'!$B$4) -> 5000000 | C4: =IF(A4="","",'Loan EMI'!$B$11) -> 43391.162 | D4: =IF(A4="","",B4*'Loan EMI'!$B$9) -> 35416.667 | E4: =IF(A4="","",C4-D4) -> 7974.495 | F4: =IF(A4="","",MAX(B4-E4,0)) -> 4992025.5
A5: =IF(2<='Loan EMI'!$B$10,2,"") -> 2 | B5: =IF(A5="","",F4) -> 4992025.5 | C5: =IF(A5="","",'Loan EMI'!$B$11) -> 43391.162 | D5: =IF(A5="","",B5*'Loan EMI'!$B$9) -> 35360.181 | E5: =IF(A5="","",C5-D5) -> 8030.981 | F5: =IF(A5="","",MAX(B5-E5,0)) -> 4983994.5
A6: =IF(3<='Loan EMI'!$B$10,3,"") -> 3 | B6: =IF(A6="","",F5) -> 4983994.5 | C6: =IF(A6="","",'Loan EMI'!$B$11) -> 43391.162 | D6: =IF(A6="","",B6*'Loan EMI'!$B$9) -> 35303.295 | E6: =IF(A6="","",C6-D6) -> 8087.8671 | F6: =IF(A6="","",MAX(B6-E6,0)) -> 4975906.7
A7: =IF(4<='Loan EMI'!$B$10,4,"") -> 4 | B7: =IF(A7="","",F6) -> 4975906.7 | C7: =IF(A7="","",'Loan EMI'!$B$11) -> 43391.162 | D7: =IF(A7="","",B7*'Loan EMI'!$B$9) -> 35246.005 | E7: =IF(A7="","",C7-D7) -> 8145.1562 | F7: =IF(A7="","",MAX(B7-E7,0)) -> 4967761.5
A8: =IF(5<='Loan EMI'!$B$10,5,"") -> 5 | B8: =IF(A8="","",F7) -> 4967761.5 | C8: =IF(A8="","",'Loan EMI'!$B$11) -> 43391.162 | D8: =IF(A8="","",B8*'Loan EMI'!$B$9) -> 35188.311 | E8: =IF(A8="","",C8-D8) -> 8202.851 | F8: =IF(A8="","",MAX(B8-E8,0)) -> 4959558.7
A9: =IF(6<='Loan EMI'!$B$10,6,"") -> 6 | B9: =IF(A9="","",F8) -> 4959558.7 | C9: =IF(A9="","",'Loan EMI'!$B$11) -> 43391.162 | D9: =IF(A9="","",B9*'Loan EMI'!$B$9) -> 35130.207 | E9: =IF(A9="","",C9-D9) -> 8260.9546 | F9: =IF(A9="","",MAX(B9-E9,0)) -> 4951297.7
A10: =IF(7<='Loan EMI'!$B$10,7,"") -> 7 | B10: =IF(A10="","",F9) -> 4951297.7 | C10: =IF(A10="","",'Loan EMI'!$B$11) -> 43391.162 | D10: =IF(A10="","",B10*'Loan EMI'!$B$9) -> 35071.692 | E10: =IF(A10="","",C10-D10) -> 8319.4697 | F10: =IF(A10="","",MAX(B10-E10,0)) -> 4942978.2
A11: =IF(8<='Loan EMI'!$B$10,8,"") -> 8 | B11: =IF(A11="","",F10) -> 4942978.2 | C11: =IF(A11="","",'Loan EMI'!$B$11) -> 43391.162 | D11: =IF(A11="","",B11*'Loan EMI'!$B$9) -> 35012.762 | E11: =IF(A11="","",C11-D11) -> 8378.3992 | F11: =IF(A11="","",MAX(B11-E11,0)) -> 4934599.8
A12: =IF(9<='Loan EMI'!$B$10,9,"") -> 9 | B12: =IF(A12="","",F11) -> 4934599.8 | C12: =IF(A12="","",'Loan EMI'!$B$11) -> 43391.162 | D12: =IF(A12="","",B12*'Loan EMI'!$B$9) -> 34953.415 | E12: =IF(A12="","",C12-D12) -> 8437.7462 | F12: =IF(A12="","",MAX(B12-E12,0)) -> 4926162.1
A13: =IF(10<='Loan EMI'!$B$10,10,"") -> 10 | B13: =IF(A13="","",F12) -> 4926162.1 | C13: =IF(A13="","",'Loan EMI'!$B$11) -> 43391.162 | D13: =IF(A13="","",B13*'Loan EMI'!$B$9) -> 34893.648 | E13: =IF(A13="","",C13-D13) -> 8497.5136 | F13: =IF(A13="","",MAX(B13-E13,0)) -> 4917664.6
A14: =IF(11<='Loan EMI'!$B$10,11,"") -> 11 | B14: =IF(A14="","",F13) -> 4917664.6 | C14: =IF(A14="","",'Loan EMI'!$B$11) -> 43391.162 | D14: =IF(A14="","",B14*'Loan EMI'!$B$9) -> 34833.457 | E14: =IF(A14="","",C14-D14) -> 8557.7043 | F14: =IF(A14="","",MAX(B14-E14,0)) -> 4909106.9
A15: =IF(12<='Loan EMI'!$B$10,12,"") -> 12 | B15: =IF(A15="","",F14) -> 4909106.9 | C15: =IF(A15="","",'Loan EMI'!$B$11) -> 43391.162 | D15: =IF(A15="","",B15*'Loan EMI'!$B$9) -> 34772.84 | E15: =IF(A15="","",C15-D15) -> 8618.3214 | F15: =IF(A15="","",MAX(B15-E15,0)) -> 4900488.5
A16: =IF(13<='Loan EMI'!$B$10,13,"") -> 13 | B16: =IF(A16="","",F15) -> 4900488.5 | C16: =IF(A16="","",'Loan EMI'!$B$11) -> 43391.162 | D16: =IF(A16="","",B16*'Loan EMI'!$B$9) -> 34711.794 | E16: =IF(A16="","",C16-D16) -> 8679.3678 | F16: =IF(A16="","",MAX(B16-E16,0)) -> 4891809.2
A17: =IF(14<='Loan EMI'!$B$10,14,"") -> 14 | B17: =IF(A17="","",F16) -> 4891809.2 | C17: =IF(A17="","",'Loan EMI'!$B$11) -> 43391.162 | D17: =IF(A17="","",B17*'Loan EMI'!$B$9) -> 34650.315 | E17: =IF(A17="","",C17-D17) -> 8740.8467 | F17: =IF(A17="","",MAX(B17-E17,0)) -> 4883068.3
A18: =IF(15<='Loan EMI'!$B$10,15,"") -> 15 | B18: =IF(A18="","",F17) -> 4883068.3 | C18: =IF(A18="","",'Loan EMI'!$B$11) -> 43391.162 | D18: =IF(A18="","",B18*'Loan EMI'!$B$9) -> 34588.401 | E18: =IF(A18="","",C18-D18) -> 8802.761 | F18: =IF(A18="","",MAX(B18-E18,0)) -> 4874265.6
A19: =IF(16<='Loan EMI'!$B$10,16,"") -> 16 | B19: =IF(A19="","",F18) -> 4874265.6 | C19: =IF(A19="","",'Loan EMI'!$B$11) -> 43391.162 | D19: =IF(A19="","",B19*'Loan EMI'!$B$9) -> 34526.048 | E19: =IF(A19="","",C19-D19) -> 8865.1139 | F19: =IF(A19="","",MAX(B19-E19,0)) -> 4865400.5
A20: =IF(17<='Loan EMI'!$B$10,17,"") -> 17 | B20: =IF(A20="","",F19) -> 4865400.5 | C20: =IF(A20="","",'Loan EMI'!$B$11) -> 43391.162 | D20: =IF(A20="","",B20*'Loan EMI'!$B$9) -> 34463.253 | E20: =IF(A20="","",C20-D20) -> 8927.9085 | F20: =IF(A20="","",MAX(B20-E20,0)) -> 4856472.5
A21: =IF(18<='Loan EMI'!$B$10,18,"") -> 18 | B21: =IF(A21="","",F20) -> 4856472.5 | C21: =IF(A21="","",'Loan EMI'!$B$11) -> 43391.162 | D21: =IF(A21="","",B21*'Loan EMI'!$B$9) -> 34400.014 | E21: =IF(A21="","",C21-D21) -> 8991.1478 | F21: =IF(A21="","",MAX(B21-E21,0)) -> 4847481.4
A22: =IF(19<='Loan EMI'!$B$10,19,"") -> 19 | B22: =IF(A22="","",F21) -> 4847481.4 | C22: =IF(A22="","",'Loan EMI'!$B$11) -> 43391.162 | D22: =IF(A22="","",B22*'Loan EMI'!$B$9) -> 34336.327 | E22: =IF(A22="","",C22-D22) -> 9054.8351 | F22: =IF(A22="","",MAX(B22-E22,0)) -> 4838426.6
A23: =IF(20<='Loan EMI'!$B$10,20,"") -> 20 | B23: =IF(A23="","",F22) -> 4838426.6 | C23: =IF(A23="","",'Loan EMI'!$B$11) -> 43391.162 | D23: =IF(A23="","",B23*'Loan EMI'!$B$9) -> 34272.188 | E23: =IF(A23="","",C23-D23) -> 9118.9735 | F23: =IF(A23="","",MAX(B23-E23,0)) -> 4829307.6
A24: =IF(21<='Loan EMI'!$B$10,21,"") -> 21 | B24: =IF(A24="","",F23) -> 4829307.6 | C24: =IF(A24="","",'Loan EMI'!$B$11) -> 43391.162 | D24: =IF(A24="","",B24*'Loan EMI'!$B$9) -> 34207.595 | E24: =IF(A24="","",C24-D24) -> 9183.5663 | F24: =IF(A24="","",MAX(B24-E24,0)) -> 4820124
A25: =IF(22<='Loan EMI'!$B$10,22,"") -> 22 | B25: =IF(A25="","",F24) -> 4820124 | C25: =IF(A25="","",'Loan EMI'!$B$11) -> 43391.162 | D25: =IF(A25="","",B25*'Loan EMI'!$B$9) -> 34142.545 | E25: =IF(A25="","",C25-D25) -> 9248.6165 | F25: =IF(A25="","",MAX(B25-E25,0)) -> 4810875.4
A26: =IF(23<='Loan EMI'!$B$10,23,"") -> 23 | B26: =IF(A26="","",F25) -> 4810875.4 | C26: =IF(A26="","",'Loan EMI'!$B$11) -> 43391.162 | D26: =IF(A26="","",B26*'Loan EMI'!$B$9) -> 34077.034 | E26: =IF(A26="","",C26-D26) -> 9314.1276 | F26: =IF(A26="","",MAX(B26-E26,0)) -> 4801561.3
A27: =IF(24<='Loan EMI'!$B$10,24,"") -> 24 | B27: =IF(A27="","",F26) -> 4801561.3 | C27: =IF(A27="","",'Loan EMI'!$B$11) -> 43391.162 | D27: =IF(A27="","",B27*'Loan EMI'!$B$9) -> 34011.059 | E27: =IF(A27="","",C27-D27) -> 9380.1026 | F27: =IF(A27="","",MAX(B27-E27,0)) -> 4792181.2
A28: =IF(25<='Loan EMI'!$B$10,25,"") -> 25 | B28: =IF(A28="","",F27) -> 4792181.2 | C28: =IF(A28="","",'Loan EMI'!$B$11) -> 43391.162 | D28: =IF(A28="","",B28*'Loan EMI'!$B$9) -> 33944.617 | E28: =IF(A28="","",C28-D28) -> 9446.545 | F28: =IF(A28="","",MAX(B28-E28,0)) -> 4782734.6
A29: =IF(26<='Loan EMI'!$B$10,26,"") -> 26 | B29: =IF(A29="","",F28) -> 4782734.6 | C29: =IF(A29="","",'Loan EMI'!$B$11) -> 43391.162 | D29: =IF(A29="","",B29*'Loan EMI'!$B$9) -> 33877.704 | E29: =IF(A29="","",C29-D29) -> 9513.4581 | F29: =IF(A29="","",MAX(B29-E29,0)) -> 4773221.2
A30: =IF(27<='Loan EMI'!$B$10,27,"") -> 27 | B30: =IF(A30="","",F29) -> 4773221.2 | C30: =IF(A30="","",'Loan EMI'!$B$11) -> 43391.162 | D30: =IF(A30="","",B30*'Loan EMI'!$B$9) -> 33810.317 | E30: =IF(A30="","",C30-D30) -> 9580.845 | F30: =IF(A30="","",MAX(B30-E30,0)) -> 4763640.3
A31: =IF(28<='Loan EMI'!$B$10,28,"") -> 28 | B31: =IF(A31="","",F30) -> 4763640.3 | C31: =IF(A31="","",'Loan EMI'!$B$11) -> 43391.162 | D31: =IF(A31="","",B31*'Loan EMI'!$B$9) -> 33742.452 | E31: =IF(A31="","",C31-D31) -> 9648.7094 | F31: =IF(A31="","",MAX(B31-E31,0)) -> 4753991.6
A32: =IF(29<='Loan EMI'!$B$10,29,"") -> 29 | B32: =IF(A32="","",F31) -> 4753991.6 | C32: =IF(A32="","",'Loan EMI'!$B$11) -> 43391.162 | D32: =IF(A32="","",B32*'Loan EMI'!$B$9) -> 33674.107 | E32: =IF(A32="","",C32-D32) -> 9717.0544 | F32: =IF(A32="","",MAX(B32-E32,0)) -> 4744274.6
A33: =IF(30<='Loan EMI'!$B$10,30,"") -> 30 | B33: =IF(A33="","",F32) -> 4744274.6 | C33: =IF(A33="","",'Loan EMI'!$B$11) -> 43391.162 | D33: =IF(A33="","",B33*'Loan EMI'!$B$9) -> 33605.278 | E33: =IF(A33="","",C33-D33) -> 9785.8835 | F33: =IF(A33="","",MAX(B33-E33,0)) -> 4734488.7
A34: =IF(31<='Loan EMI'!$B$10,31,"") -> 31 | B34: =IF(A34="","",F33) -> 4734488.7 | C34: =IF(A34="","",'Loan EMI'!$B$11) -> 43391.162 | D34: =IF(A34="","",B34*'Loan EMI'!$B$9) -> 33535.961 | E34: =IF(A34="","",C34-D34) -> 9855.2002 | F34: =IF(A34="","",MAX(B34-E34,0)) -> 4724633.5
A35: =IF(32<='Loan EMI'!$B$10,32,"") -> 32 | B35: =IF(A35="","",F34) -> 4724633.5 | C35: =IF(A35="","",'Loan EMI'!$B$11) -> 43391.162 | D35: =IF(A35="","",B35*'Loan EMI'!$B$9) -> 33466.154 | E35: =IF(A35="","",C35-D35) -> 9925.0079 | F35: =IF(A35="","",MAX(B35-E35,0)) -> 4714708.5
A36: =IF(33<='Loan EMI'!$B$10,33,"") -> 33 | B36: =IF(A36="","",F35) -> 4714708.5 | C36: =IF(A36="","",'Loan EMI'!$B$11) -> 43391.162 | D36: =IF(A36="","",B36*'Loan EMI'!$B$9) -> 33395.852 | E36: =IF(A36="","",C36-D36) -> 9995.31 | F36: =IF(A36="","",MAX(B36-E36,0)) -> 4704713.2
A37: =IF(34<='Loan EMI'!$B$10,34,"") -> 34 | B37: =IF(A37="","",F36) -> 4704713.2 | C37: =IF(A37="","",'Loan EMI'!$B$11) -> 43391.162 | D37: =IF(A37="","",B37*'Loan EMI'!$B$9) -> 33325.052 | E37: =IF(A37="","",C37-D37) -> 10066.11 | F37: =IF(A37="","",MAX(B37-E37,0)) -> 4694647
A38: =IF(35<='Loan EMI'!$B$10,35,"") -> 35 | B38: =IF(A38="","",F37) -> 4694647 | C38: =IF(A38="","",'Loan EMI'!$B$11) -> 43391.162 | D38: =IF(A38="","",B38*'Loan EMI'!$B$9) -> 33253.75 | E38: =IF(A38="","",C38-D38) -> 10137.412 | F38: =IF(A38="","",MAX(B38-E38,0)) -> 4684509.6
A39: =IF(36<='Loan EMI'!$B$10,36,"") -> 36 | B39: =IF(A39="","",F38) -> 4684509.6 | C39: =IF(A39="","",'Loan EMI'!$B$11) -> 43391.162 | D39: =IF(A39="","",B39*'Loan EMI'!$B$9) -> 33181.943 | E39: =IF(A39="","",C39-D39) -> 10209.218 | F39: =IF(A39="","",MAX(B39-E39,0)) -> 4674300.4
A40: =IF(37<='Loan EMI'!$B$10,37,"") -> 37 | B40: =IF(A40="","",F39) -> 4674300.4 | C40: =IF(A40="","",'Loan EMI'!$B$11) -> 43391.162 | D40: =IF(A40="","",B40*'Loan EMI'!$B$9) -> 33109.628 | E40: =IF(A40="","",C40-D40) -> 10281.534 | F40: =IF(A40="","",MAX(B40-E40,0)) -> 4664018.9
A41: =IF(38<='Loan EMI'!$B$10,38,"") -> 38 | B41: =IF(A41="","",F40) -> 4664018.9 | C41: =IF(A41="","",'Loan EMI'!$B$11) -> 43391.162 | D41: =IF(A41="","",B41*'Loan EMI'!$B$9) -> 33036.8 | E41: =IF(A41="","",C41-D41) -> 10354.361 | F41: =IF(A41="","",MAX(B41-E41,0)) -> 4653664.5
A42: =IF(39<='Loan EMI'!$B$10,39,"") -> 39 | B42: =IF(A42="","",F41) -> 4653664.5 | C42: =IF(A42="","",'Loan EMI'!$B$11) -> 43391.162 | D42: =IF(A42="","",B42*'Loan EMI'!$B$9) -> 32963.457 | E42: =IF(A42="","",C42-D42) -> 10427.705 | F42: =IF(A42="","",MAX(B42-E42,0)) -> 4643236.8
A43: =IF(40<='Loan EMI'!$B$10,40,"") -> 40 | B43: =IF(A43="","",F42) -> 4643236.8 | C43: =IF(A43="","",'Loan EMI'!$B$11) -> 43391.162 | D43: =IF(A43="","",B43*'Loan EMI'!$B$9) -> 32889.594 | E43: =IF(A43="","",C43-D43) -> 10501.568 | F43: =IF(A43="","",MAX(B43-E43,0)) -> 4632735.3
A44: =IF(41<='Loan EMI'!$B$10,41,"") -> 41 | B44: =IF(A44="","",F43) -> 4632735.3 | C44: =IF(A44="","",'Loan EMI'!$B$11) -> 43391.162 | D44: =IF(A44="","",B44*'Loan EMI'!$B$9) -> 32815.208 | E44: =IF(A44="","",C44-D44) -> 10575.954 | F44: =IF(A44="","",MAX(B44-E44,0)) -> 4622159.3
A45: =IF(42<='Loan EMI'!$B$10,42,"") -> 42 | B45: =IF(A45="","",F44) -> 4622159.3 | C45: =IF(A45="","",'Loan EMI'!$B$11) -> 43391.162 | D45: =IF(A45="","",B45*'Loan EMI'!$B$9) -> 32740.295 | E45: =IF(A45="","",C45-D45) -> 10650.867 | F45: =IF(A45="","",MAX(B45-E45,0)) -> 4611508.4
A46: =IF(43<='Loan EMI'!$B$10,43,"") -> 43 | B46: =IF(A46="","",F45) -> 4611508.4 | C46: =IF(A46="","",'Loan EMI'!$B$11) -> 43391.162 | D46: =IF(A46="","",B46*'Loan EMI'!$B$9) -> 32664.851 | E46: =IF(A46="","",C46-D46) -> 10726.31 | F46: =IF(A46="","",MAX(B46-E46,0)) -> 4600782.1
A47: =IF(44<='Loan EMI'!$B$10,44,"") -> 44 | B47: =IF(A47="","",F46) -> 4600782.1 | C47: =IF(A47="","",'Loan EMI'!$B$11) -> 43391.162 | D47: =IF(A47="","",B47*'Loan EMI'!$B$9) -> 32588.873 | E47: =IF(A47="","",C47-D47) -> 10802.288 | F47: =IF(A47="","",MAX(B47-E47,0)) -> 4589979.8
A48: =IF(45<='Loan EMI'!$B$10,45,"") -> 45 | B48: =IF(A48="","",F47) -> 4589979.8 | C48: =IF(A48="","",'Loan EMI'!$B$11) -> 43391.162 | D48: =IF(A48="","",B48*'Loan EMI'!$B$9) -> 32512.357 | E48: =IF(A48="","",C48-D48) -> 10878.805 | F48: =IF(A48="","",MAX(B48-E48,0)) -> 4579101
A49: =IF(46<='Loan EMI'!$B$10,46,"") -> 46 | B49: =IF(A49="","",F48) -> 4579101 | C49: =IF(A49="","",'Loan EMI'!$B$11) -> 43391.162 | D49: =IF(A49="","",B49*'Loan EMI'!$B$9) -> 32435.299 | E49: =IF(A49="","",C49-D49) -> 10955.863 | F49: =IF(A49="","",MAX(B49-E49,0)) -> 4568145.2
A50: =IF(47<='Loan EMI'!$B$10,47,"") -> 47 | B50: =IF(A50="","",F49) -> 4568145.2 | C50: =IF(A50="","",'Loan EMI'!$B$11) -> 43391.162 | D50: =IF(A50="","",B50*'Loan EMI'!$B$9) -> 32357.695 | E50: =IF(A50="","",C50-D50) -> 11033.467 | F50: =IF(A50="","",MAX(B50-E50,0)) -> 4557111.7
A51: =IF(48<='Loan EMI'!$B$10,48,"") -> 48 | B51: =IF(A51="","",F50) -> 4557111.7 | C51: =IF(A51="","",'Loan EMI'!$B$11) -> 43391.162 | D51: =IF(A51="","",B51*'Loan EMI'!$B$9) -> 32279.541 | E51: =IF(A51="","",C51-D51) -> 11111.62 | F51: =IF(A51="","",MAX(B51-E51,0)) -> 4546000.1
A52: =IF(49<='Loan EMI'!$B$10,49,"") -> 49 | B52: =IF(A52="","",F51) -> 4546000.1 | C52: =IF(A52="","",'Loan EMI'!$B$11) -> 43391.162 | D52: =IF(A52="","",B52*'Loan EMI'!$B$9) -> 32200.834 | E52: =IF(A52="","",C52-D52) -> 11190.328 | F52: =IF(A52="","",MAX(B52-E52,0)) -> 4534809.8
A53: =IF(50<='Loan EMI'!$B$10,50,"") -> 50 | B53: =IF(A53="","",F52) -> 4534809.8 | C53: =IF(A53="","",'Loan EMI'!$B$11) -> 43391.162 | D53: =IF(A53="","",B53*'Loan EMI'!$B$9) -> 32121.569 | E53: =IF(A53="","",C53-D53) -> 11269.593 | F53: =IF(A53="","",MAX(B53-E53,0)) -> 4523540.2
A54: =IF(51<='Loan EMI'!$B$10,51,"") -> 51 | B54: =IF(A54="","",F53) -> 4523540.2 | C54: =IF(A54="","",'Loan EMI'!$B$11) -> 43391.162 | D54: =IF(A54="","",B54*'Loan EMI'!$B$9) -> 32041.743 | E54: =IF(A54="","",C54-D54) -> 11349.419 | F54: =IF(A54="","",MAX(B54-E54,0)) -> 4512190.7
A55: =IF(52<='Loan EMI'!$B$10,52,"") -> 52 | B55: =IF(A55="","",F54) -> 4512190.7 | C55: =IF(A55="","",'Loan EMI'!$B$11) -> 43391.162 | D55: =IF(A55="","",B55*'Loan EMI'!$B$9) -> 31961.351 | E55: =IF(A55="","",C55-D55) -> 11429.811 | F55: =IF(A55="","",MAX(B55-E55,0)) -> 4500760.9
A56: =IF(53<='Loan EMI'!$B$10,53,"") -> 53 | B56: =IF(A56="","",F55) -> 4500760.9 | C56: =IF(A56="","",'Loan EMI'!$B$11) -> 43391.162 | D56: =IF(A56="","",B56*'Loan EMI'!$B$9) -> 31880.39 | E56: =IF(A56="","",C56-D56) -> 11510.772 | F56: =IF(A56="","",MAX(B56-E56,0)) -> 4489250.2
A57: =IF(54<='Loan EMI'!$B$10,54,"") -> 54 | B57: =IF(A57="","",F56) -> 4489250.2 | C57: =IF(A57="","",'Loan EMI'!$B$11) -> 43391.162 | D57: =IF(A57="","",B57*'Loan EMI'!$B$9) -> 31798.855 | E57: =IF(A57="","",C57-D57) -> 11592.306 | F57: =IF(A57="","",MAX(B57-E57,0)) -> 4477657.9
A58: =IF(55<='Loan EMI'!$B$10,55,"") -> 55 | B58: =IF(A58="","",F57) -> 4477657.9 | C58: =IF(A58="","",'Loan EMI'!$B$11) -> 43391.162 | D58: =IF(A58="","",B58*'Loan EMI'!$B$9) -> 31716.743 | E58: =IF(A58="","",C58-D58) -> 11674.419 | F58: =IF(A58="","",MAX(B58-E58,0)) -> 4465983.4
A59: =IF(56<='Loan EMI'!$B$10,56,"") -> 56 | B59: =IF(A59="","",F58) -> 4465983.4 | C59: =IF(A59="","",'Loan EMI'!$B$11) -> 43391.162 | D59: =IF(A59="","",B59*'Loan EMI'!$B$9) -> 31634.049 | E59: =IF(A59="","",C59-D59) -> 11757.112 | F59: =IF(A59="","",MAX(B59-E59,0)) -> 4454226.3
A60: =IF(57<='Loan EMI'!$B$10,57,"") -> 57 | B60: =IF(A60="","",F59) -> 4454226.3 | C60: =IF(A60="","",'Loan EMI'!$B$11) -> 43391.162 | D60: =IF(A60="","",B60*'Loan EMI'!$B$9) -> 31550.77 | E60: =IF(A60="","",C60-D60) -> 11840.392 | F60: =IF(A60="","",MAX(B60-E60,0)) -> 4442385.9
A61: =IF(58<='Loan EMI'!$B$10,58,"") -> 58 | B61: =IF(A61="","",F60) -> 4442385.9 | C61: =IF(A61="","",'Loan EMI'!$B$11) -> 43391.162 | D61: =IF(A61="","",B61*'Loan EMI'!$B$9) -> 31466.9 | E61: =IF(A61="","",C61-D61) -> 11924.261 | F61: =IF(A61="","",MAX(B61-E61,0)) -> 4430461.7
A62: =IF(59<='Loan EMI'!$B$10,59,"") -> 59 | B62: =IF(A62="","",F61) -> 4430461.7 | C62: =IF(A62="","",'Loan EMI'!$B$11) -> 43391.162 | D62: =IF(A62="","",B62*'Loan EMI'!$B$9) -> 31382.437 | E62: =IF(A62="","",C62-D62) -> 12008.725 | F62: =IF(A62="","",MAX(B62-E62,0)) -> 4418452.9
A63: =IF(60<='Loan EMI'!$B$10,60,"") -> 60 | B63: =IF(A63="","",F62) -> 4418452.9 | C63: =IF(A63="","",'Loan EMI'!$B$11) -> 43391.162 | D63: =IF(A63="","",B63*'Loan EMI'!$B$9) -> 31297.375 | E63: =IF(A63="","",C63-D63) -> 12093.787 | F63: =IF(A63="","",MAX(B63-E63,0)) -> 4406359.2
A64: =IF(61<='Loan EMI'!$B$10,61,"") -> 61 | B64: =IF(A64="","",F63) -> 4406359.2 | C64: =IF(A64="","",'Loan EMI'!$B$11) -> 43391.162 | D64: =IF(A64="","",B64*'Loan EMI'!$B$9) -> 31211.711 | E64: =IF(A64="","",C64-D64) -> 12179.451 | F64: =IF(A64="","",MAX(B64-E64,0)) -> 4394179.7
A65: =IF(62<='Loan EMI'!$B$10,62,"") -> 62 | B65: =IF(A65="","",F64) -> 4394179.7 | C65: =IF(A65="","",'Loan EMI'!$B$11) -> 43391.162 | D65: =IF(A65="","",B65*'Loan EMI'!$B$9) -> 31125.44 | E65: =IF(A65="","",C65-D65) -> 12265.722 | F65: =IF(A65="","",MAX(B65-E65,0)) -> 4381914
A66: =IF(63<='Loan EMI'!$B$10,63,"") -> 63 | B66: =IF(A66="","",F65) -> 4381914 | C66: =IF(A66="","",'Loan EMI'!$B$11) -> 43391.162 | D66: =IF(A66="","",B66*'Loan EMI'!$B$9) -> 31038.557 | E66: =IF(A66="","",C66-D66) -> 12352.604 | F66: =IF(A66="","",MAX(B66-E66,0)) -> 4369561.4
A67: =IF(64<='Loan EMI'!$B$10,64,"") -> 64 | B67: =IF(A67="","",F66) -> 4369561.4 | C67: =IF(A67="","",'Loan EMI'!$B$11) -> 43391.162 | D67: =IF(A67="","",B67*'Loan EMI'!$B$9) -> 30951.06 | E67: =IF(A67="","",C67-D67) -> 12440.102 | F67: =IF(A67="","",MAX(B67-E67,0)) -> 4357121.3
A68: =IF(65<='Loan EMI'!$B$10,65,"") -> 65 | B68: =IF(A68="","",F67) -> 4357121.3 | C68: =IF(A68="","",'Loan EMI'!$B$11) -> 43391.162 | D68: =IF(A68="","",B68*'Loan EMI'!$B$9) -> 30862.942 | E68: =IF(A68="","",C68-D68) -> 12528.219 | F68: =IF(A68="","",MAX(B68-E68,0)) -> 4344593.1
A69: =IF(66<='Loan EMI'!$B$10,66,"") -> 66 | B69: =IF(A69="","",F68) -> 4344593.1 | C69: =IF(A69="","",'Loan EMI'!$B$11) -> 43391.162 | D69: =IF(A69="","",B69*'Loan EMI'!$B$9) -> 30774.201 | E69: =IF(A69="","",C69-D69) -> 12616.961 | F69: =IF(A69="","",MAX(B69-E69,0)) -> 4331976.1
A70: =IF(67<='Loan EMI'!$B$10,67,"") -> 67 | B70: =IF(A70="","",F69) -> 4331976.1 | C70: =IF(A70="","",'Loan EMI'!$B$11) -> 43391.162 | D70: =IF(A70="","",B70*'Loan EMI'!$B$9) -> 30684.831 | E70: =IF(A70="","",C70-D70) -> 12706.331 | F70: =IF(A70="","",MAX(B70-E70,0)) -> 4319269.8
A71: =IF(68<='Loan EMI'!$B$10,68,"") -> 68 | B71: =IF(A71="","",F70) -> 4319269.8 | C71: =IF(A71="","",'Loan EMI'!$B$11) -> 43391.162 | D71: =IF(A71="","",B71*'Loan EMI'!$B$9) -> 30594.827 | E71: =IF(A71="","",C71-D71) -> 12796.334 | F71: =IF(A71="","",MAX(B71-E71,0)) -> 4306473.4
A72: =IF(69<='Loan EMI'!$B$10,69,"") -> 69 | B72: =IF(A72="","",F71) -> 4306473.4 | C72: =IF(A72="","",'Loan EMI'!$B$11) -> 43391.162 | D72: =IF(A72="","",B72*'Loan EMI'!$B$9) -> 30504.187 | E72: =IF(A72="","",C72-D72) -> 12886.975 | F72: =IF(A72="","",MAX(B72-E72,0)) -> 4293586.5
A73: =IF(70<='Loan EMI'!$B$10,70,"") -> 70 | B73: =IF(A73="","",F72) -> 4293586.5 | C73: =IF(A73="","",'Loan EMI'!$B$11) -> 43391.162 | D73: =IF(A73="","",B73*'Loan EMI'!$B$9) -> 30412.904 | E73: =IF(A73="","",C73-D73) -> 12978.258 | F73: =IF(A73="","",MAX(B73-E73,0)) -> 4280608.2
A74: =IF(71<='Loan EMI'!$B$10,71,"") -> 71 | B74: =IF(A74="","",F73) -> 4280608.2 | C74: =IF(A74="","",'Loan EMI'!$B$11) -> 43391.162 | D74: =IF(A74="","",B74*'Loan EMI'!$B$9) -> 30320.975 | E74: =IF(A74="","",C74-D74) -> 13070.187 | F74: =IF(A74="","",MAX(B74-E74,0)) -> 4267538
A75: =IF(72<='Loan EMI'!$B$10,72,"") -> 72 | B75: =IF(A75="","",F74) -> 4267538 | C75: =IF(A75="","",'Loan EMI'!$B$11) -> 43391.162 | D75: =IF(A75="","",B75*'Loan EMI'!$B$9) -> 30228.394 | E75: =IF(A75="","",C75-D75) -> 13162.767 | F75: =IF(A75="","",MAX(B75-E75,0)) -> 4254375.2
A76: =IF(73<='Loan EMI'!$B$10,73,"") -> 73 | B76: =IF(A76="","",F75) -> 4254375.2 | C76: =IF(A76="","",'Loan EMI'!$B$11) -> 43391.162 | D76: =IF(A76="","",B76*'Loan EMI'!$B$9) -> 30135.158 | E76: =IF(A76="","",C76-D76) -> 13256.004 | F76: =IF(A76="","",MAX(B76-E76,0)) -> 4241119.2
A77: =IF(74<='Loan EMI'!$B$10,74,"") -> 74 | B77: =IF(A77="","",F76) -> 4241119.2 | C77: =IF(A77="","",'Loan EMI'!$B$11) -> 43391.162 | D77: =IF(A77="","",B77*'Loan EMI'!$B$9) -> 30041.261 | E77: =IF(A77="","",C77-D77) -> 13349.9 | F77: =IF(A77="","",MAX(B77-E77,0)) -> 4227769.3
A78: =IF(75<='Loan EMI'!$B$10,75,"") -> 75 | B78: =IF(A78="","",F77) -> 4227769.3 | C78: =IF(A78="","",'Loan EMI'!$B$11) -> 43391.162 | D78: =IF(A78="","",B78*'Loan EMI'!$B$9) -> 29946.699 | E78: =IF(A78="","",C78-D78) -> 13444.462 | F78: =IF(A78="","",MAX(B78-E78,0)) -> 4214324.9
A79: =IF(76<='Loan EMI'!$B$10,76,"") -> 76 | B79: =IF(A79="","",F78) -> 4214324.9 | C79: =IF(A79="","",'Loan EMI'!$B$11) -> 43391.162 | D79: =IF(A79="","",B79*'Loan EMI'!$B$9) -> 29851.468 | E79: =IF(A79="","",C79-D79) -> 13539.694 | F79: =IF(A79="","",MAX(B79-E79,0)) -> 4200785.2
A80: =IF(77<='Loan EMI'!$B$10,77,"") -> 77 | B80: =IF(A80="","",F79) -> 4200785.2 | C80: =IF(A80="","",'Loan EMI'!$B$11) -> 43391.162 | D80: =IF(A80="","",B80*'Loan EMI'!$B$9) -> 29755.562 | E80: =IF(A80="","",C80-D80) -> 13635.6 | F80: =IF(A80="","",MAX(B80-E80,0)) -> 4187149.6
A81: =IF(78<='Loan EMI'!$B$10,78,"") -> 78 | B81: =IF(A81="","",F80) -> 4187149.6 | C81: =IF(A81="","",'Loan EMI'!$B$11) -> 43391.162 | D81: =IF(A81="","",B81*'Loan EMI'!$B$9) -> 29658.976 | E81: =IF(A81="","",C81-D81) -> 13732.185 | F81: =IF(A81="","",MAX(B81-E81,0)) -> 4173417.4
A82: =IF(79<='Loan EMI'!$B$10,79,"") -> 79 | B82: =IF(A82="","",F81) -> 4173417.4 | C82: =IF(A82="","",'Loan EMI'!$B$11) -> 43391.162 | D82: =IF(A82="","",B82*'Loan EMI'!$B$9) -> 29561.707 | E82: =IF(A82="","",C82-D82) -> 13829.455 | F82: =IF(A82="","",MAX(B82-E82,0)) -> 4159587.9
A83: =IF(80<='Loan EMI'!$B$10,80,"") -> 80 | B83: =IF(A83="","",F82) -> 4159587.9 | C83: =IF(A83="","",'Loan EMI'!$B$11) -> 43391.162 | D83: =IF(A83="","",B83*'Loan EMI'!$B$9) -> 29463.748 | E83: =IF(A83="","",C83-D83) -> 13927.414 | F83: =IF(A83="","",MAX(B83-E83,0)) -> 4145660.5
A84: =IF(81<='Loan EMI'!$B$10,81,"") -> 81 | B84: =IF(A84="","",F83) -> 4145660.5 | C84: =IF(A84="","",'Loan EMI'!$B$11) -> 43391.162 | D84: =IF(A84="","",B84*'Loan EMI'!$B$9) -> 29365.095 | E84: =IF(A84="","",C84-D84) -> 14026.066 | F84: =IF(A84="","",MAX(B84-E84,0)) -> 4131634.5
A85: =IF(82<='Loan EMI'!$B$10,82,"") -> 82 | B85: =IF(A85="","",F84) -> 4131634.5 | C85: =IF(A85="","",'Loan EMI'!$B$11) -> 43391.162 | D85: =IF(A85="","",B85*'Loan EMI'!$B$9) -> 29265.744 | E85: =IF(A85="","",C85-D85) -> 14125.418 | F85: =IF(A85="","",MAX(B85-E85,0)) -> 4117509
A86: =IF(83<='Loan EMI'!$B$10,83,"") -> 83 | B86: =IF(A86="","",F85) -> 4117509 | C86: =IF(A86="","",'Loan EMI'!$B$11) -> 43391.162 | D86: =IF(A86="","",B86*'Loan EMI'!$B$9) -> 29165.689 | E86: =IF(A86="","",C86-D86) -> 14225.473 | F86: =IF(A86="","",MAX(B86-E86,0)) -> 4103283.6
A87: =IF(84<='Loan EMI'!$B$10,84,"") -> 84 | B87: =IF(A87="","",F86) -> 4103283.6 | C87: =IF(A87="","",'Loan EMI'!$B$11) -> 43391.162 | D87: =IF(A87="","",B87*'Loan EMI'!$B$9) -> 29064.925 | E87: =IF(A87="","",C87-D87) -> 14326.236 | F87: =IF(A87="","",MAX(B87-E87,0)) -> 4088957.3
A88: =IF(85<='Loan EMI'!$B$10,85,"") -> 85 | B88: =IF(A88="","",F87) -> 4088957.3 | C88: =IF(A88="","",'Loan EMI'!$B$11) -> 43391.162 | D88: =IF(A88="","",B88*'Loan EMI'!$B$9) -> 28963.448 | E88: =IF(A88="","",C88-D88) -> 14427.714 | F88: =IF(A88="","",MAX(B88-E88,0)) -> 4074529.6
A89: =IF(86<='Loan EMI'!$B$10,86,"") -> 86 | B89: =IF(A89="","",F88) -> 4074529.6 | C89: =IF(A89="","",'Loan EMI'!$B$11) -> 43391.162 | D89: =IF(A89="","",B89*'Loan EMI'!$B$9) -> 28861.251 | E89: =IF(A89="","",C89-D89) -> 14529.91 | F89: =IF(A89="","",MAX(B89-E89,0)) -> 4059999.7
A90: =IF(87<='Loan EMI'!$B$10,87,"") -> 87 | B90: =IF(A90="","",F89) -> 4059999.7 | C90: =IF(A90="","",'Loan EMI'!$B$11) -> 43391.162 | D90: =IF(A90="","",B90*'Loan EMI'!$B$9) -> 28758.331 | E90: =IF(A90="","",C90-D90) -> 14632.83 | F90: =IF(A90="","",MAX(B90-E90,0)) -> 4045366.9
A91: =IF(88<='Loan EMI'!$B$10,88,"") -> 88 | B91: =IF(A91="","",F90) -> 4045366.9 | C91: =IF(A91="","",'Loan EMI'!$B$11) -> 43391.162 | D91: =IF(A91="","",B91*'Loan EMI'!$B$9) -> 28654.682 | E91: =IF(A91="","",C91-D91) -> 14736.48 | F91: =IF(A91="","",MAX(B91-E91,0)) -> 4030630.4
A92: =IF(89<='Loan EMI'!$B$10,89,"") -> 89 | B92: =IF(A92="","",F91) -> 4030630.4 | C92: =IF(A92="","",'Loan EMI'!$B$11) -> 43391.162 | D92: =IF(A92="","",B92*'Loan EMI'!$B$9) -> 28550.299 | E92: =IF(A92="","",C92-D92) -> 14840.863 | F92: =IF(A92="","",MAX(B92-E92,0)) -> 4015789.5
A93: =IF(90<='Loan EMI'!$B$10,90,"") -> 90 | B93: =IF(A93="","",F92) -> 4015789.5 | C93: =IF(A93="","",'Loan EMI'!$B$11) -> 43391.162 | D93: =IF(A93="","",B93*'Loan EMI'!$B$9) -> 28445.176 | E93: =IF(A93="","",C93-D93) -> 14945.986 | F93: =IF(A93="","",MAX(B93-E93,0)) -> 4000843.6
A94: =IF(91<='Loan EMI'!$B$10,91,"") -> 91 | B94: =IF(A94="","",F93) -> 4000843.6 | C94: =IF(A94="","",'Loan EMI'!$B$11) -> 43391.162 | D94: =IF(A94="","",B94*'Loan EMI'!$B$9) -> 28339.309 | E94: =IF(A94="","",C94-D94) -> 15051.853 | F94: =IF(A94="","",MAX(B94-E94,0)) -> 3985791.7
A95: =IF(92<='Loan EMI'!$B$10,92,"") -> 92 | B95: =IF(A95="","",F94) -> 3985791.7 | C95: =IF(A95="","",'Loan EMI'!$B$11) -> 43391.162 | D95: =IF(A95="","",B95*'Loan EMI'!$B$9) -> 28232.691 | E95: =IF(A95="","",C95-D95) -> 15158.47 | F95: =IF(A95="","",MAX(B95-E95,0)) -> 3970633.2
A96: =IF(93<='Loan EMI'!$B$10,93,"") -> 93 | B96: =IF(A96="","",F95) -> 3970633.2 | C96: =IF(A96="","",'Loan EMI'!$B$11) -> 43391.162 | D96: =IF(A96="","",B96*'Loan EMI'!$B$9) -> 28125.319 | E96: =IF(A96="","",C96-D96) -> 15265.843 | F96: =IF(A96="","",MAX(B96-E96,0)) -> 3955367.4
A97: =IF(94<='Loan EMI'!$B$10,94,"") -> 94 | B97: =IF(A97="","",F96) -> 3955367.4 | C97: =IF(A97="","",'Loan EMI'!$B$11) -> 43391.162 | D97: =IF(A97="","",B97*'Loan EMI'!$B$9) -> 28017.186 | E97: =IF(A97="","",C97-D97) -> 15373.976 | F97: =IF(A97="","",MAX(B97-E97,0)) -> 3939993.4
A98: =IF(95<='Loan EMI'!$B$10,95,"") -> 95 | B98: =IF(A98="","",F97) -> 3939993.4 | C98: =IF(A98="","",'Loan EMI'!$B$11) -> 43391.162 | D98: =IF(A98="","",B98*'Loan EMI'!$B$9) -> 27908.287 | E98: =IF(A98="","",C98-D98) -> 15482.875 | F98: =IF(A98="","",MAX(B98-E98,0)) -> 3924510.5
A99: =IF(96<='Loan EMI'!$B$10,96,"") -> 96 | B99: =IF(A99="","",F98) -> 3924510.5 | C99: =IF(A99="","",'Loan EMI'!$B$11) -> 43391.162 | D99: =IF(A99="","",B99*'Loan EMI'!$B$9) -> 27798.616 | E99: =IF(A99="","",C99-D99) -> 15592.545 | F99: =IF(A99="","",MAX(B99-E99,0)) -> 3908918
A100: =IF(97<='Loan EMI'!$B$10,97,"") -> 97 | B100: =IF(A100="","",F99) -> 3908918 | C100: =IF(A100="","",'Loan EMI'!$B$11) -> 43391.162 | D100: =IF(A100="","",B100*'Loan EMI'!$B$9) -> 27688.169 | E100: =IF(A100="","",C100-D100) -> 15702.993 | F100: =IF(A100="","",MAX(B100-E100,0)) -> 3893215
A101: =IF(98<='Loan EMI'!$B$10,98,"") -> 98 | B101: =IF(A101="","",F100) -> 3893215 | C101: =IF(A101="","",'Loan EMI'!$B$11) -> 43391.162 | D101: =IF(A101="","",B101*'Loan EMI'!$B$9) -> 27576.94 | E101: =IF(A101="","",C101-D101) -> 15814.222 | F101: =IF(A101="","",MAX(B101-E101,0)) -> 3877400.8
...

Sheet SIP Planner
A1: SIP (Systematic Investment Plan) Planner
A2: Edit only the blue cells with yellow fill. Returns are an assumption, not a guarantee.
A4: Monthly SIP amount | B4: 10000
A5: Expected annual return | B5: 0.12
A6: Investment period (years) | B6: 15
A7: Annual step-up in SIP | B7: 0
A9: Results
A10: Total invested | B10: =SUM(B19:B48) -> 1800000
A11: Final corpus value | B11: {=IFERROR(INDEX(E19:E48,B6),0)} -> 4759314
A12: Wealth gained | B12: =B11-B10 -> 2959314
A13: Corpus / invested (x) | B13: =IFERROR(B11/B10,0) -> 2.6440633
A14: Year-wise growth (monthly compounding; SIP invested at start of each month; step-up applied yearly).
A15: Monthly return used | B15: =(1+B5)^(1/12)-1 -> 0.0094887929
A18: Year | B18: Invested in year | C18: Cumulative invested | D18: Monthly SIP in year | E18: Corpus at year end
A19: =IF(1<=$B$6,1,"") -> 1 | B19: =IF(A19="","",D19*12) -> 120000 | C19: =IF(A19="","",SUM($B$19:B19)) -> 120000 | D19: =IF(A19="","",$B$4*(1+$B$7)^(1-1)) -> 10000 | E19: =IF(A19="","",0*(1+$B$15)^12+D19*((1+$B$15)^12-1)/$B$15*(1+$B$15)) -> 127664.98
A20: =IF(2<=$B$6,2,"") -> 2 | B20: =IF(A20="","",D20*12) -> 120000 | C20: =IF(A20="","",SUM($B$19:B20)) -> 240000 | D20: =IF(A20="","",$B$4*(1+$B$7)^(2-1)) -> 10000 | E20: =IF(A20="","",E19*(1+$B$15)^12+D20*((1+$B$15)^12-1)/$B$15*(1+$B$15)) -> 270649.76
A21: =IF(3<=$B$6,3,"") -> 3 | B21: =IF(A21="","",D21*12) -> 120000 | C21: =IF(A21="","",SUM($B$19:B21)) -> 360000 | D21: =IF(A21="","",$B$4*(1+$B$7)^(3-1)) -> 10000 | E21: =IF(A21="","",E20*(1+$B$15)^12+D21*((1+$B$15)^12-1)/$B$15*(1+$B$15)) -> 430792.71
A22: =IF(4<=$B$6,4,"") -> 4 | B22: =IF(A22="","",D22*12) -> 120000 | C22: =IF(A22="","",SUM($B$19:B22)) -> 480000 | D22: =IF(A22="","",$B$4*(1+$B$7)^(4-1)) -> 10000 | E22: =IF(A22="","",E21*(1+$B$15)^12+D22*((1+$B$15)^12-1)/$B$15*(1+$B$15)) -> 610152.81
A23: =IF(5<=$B$6,5,"") -> 5 | B23: =IF(A23="","",D23*12) -> 120000 | C23: =IF(A23="","",SUM($B$19:B23)) -> 600000 | D23: =IF(A23="","",$B$4*(1+$B$7)^(5-1)) -> 10000 | E23: =IF(A23="","",E22*(1+$B$15)^12+D23*((1+$B$15)^12-1)/$B$15*(1+$B$15)) -> 811036.13
A24: =IF(6<=$B$6,6,"") -> 6 | B24: =IF(A24="","",D24*12) -> 120000 | C24: =IF(A24="","",SUM($B$19:B24)) -> 720000 | D24: =IF(A24="","",$B$4*(1+$B$7)^(6-1)) -> 10000 | E24: =IF(A24="","",E23*(1+$B$15)^12+D24*((1+$B$15)^12-1)/$B$15*(1+$B$15)) -> 1036025.4
A25: =IF(7<=$B$6,7,"") -> 7 | B25: =IF(A25="","",D25*12) -> 120000 | C25: =IF(A25="","",SUM($B$19:B25)) -> 840000 | D25: =IF(A25="","",$B$4*(1+$B$7)^(7-1)) -> 10000 | E25: =IF(A25="","",E24*(1+$B$15)^12+D25*((1+$B$15)^12-1)/$B$15*(1+$B$15)) -> 1288013.5
A26: =IF(8<=$B$6,8,"") -> 8 | B26: =IF(A26="","",D26*12) -> 120000 | C26: =IF(A26="","",SUM($B$19:B26)) -> 960000 | D26: =IF(A26="","",$B$4*(1+$B$7)^(8-1)) -> 10000 | E26: =IF(A26="","",E25*(1+$B$15)^12+D26*((1+$B$15)^12-1)/$B$15*(1+$B$15)) -> 1570240.1
A27: =IF(9<=$B$6,9,"") -> 9 | B27: =IF(A27="","",D27*12) -> 120000 | C27: =IF(A27="","",SUM($B$19:B27)) -> 1080000 | D27: =IF(A27="","",$B$4*(1+$B$7)^(9-1)) -> 10000 | E27: =IF(A27="","",E26*(1+$B$15)^12+D27*((1+$B$15)^12-1)/$B$15*(1+$B$15)) -> 1886333.9
A28: =IF(10<=$B$6,10,"") -> 10 | B28: =IF(A28="","",D28*12) -> 120000 | C28: =IF(A28="","",SUM($B$19:B28)) -> 1200000 | D28: =IF(A28="","",$B$4*(1+$B$7)^(10-1)) -> 10000 | E28: =IF(A28="","",E27*(1+$B$15)^12+D28*((1+$B$15)^12-1)/$B$15*(1+$B$15)) -> 2240358.9
A29: =IF(11<=$B$6,11,"") -> 11 | B29: =IF(A29="","",D29*12) -> 120000 | C29: =IF(A29="","",SUM($B$19:B29)) -> 1320000 | D29: =IF(A29="","",$B$4*(1+$B$7)^(11-1)) -> 10000 | E29: =IF(A29="","",E28*(1+$B$15)^12+D29*((1+$B$15)^12-1)/$B$15*(1+$B$15)) -> 2636866.9
A30: =IF(12<=$B$6,12,"") -> 12 | B30: =IF(A30="","",D30*12) -> 120000 | C30: =IF(A30="","",SUM($B$19:B30)) -> 1440000 | D30: =IF(A30="","",$B$4*(1+$B$7)^(12-1)) -> 10000 | E30: =IF(A30="","",E29*(1+$B$15)^12+D30*((1+$B$15)^12-1)/$B$15*(1+$B$15)) -> 3080956
A31: =IF(13<=$B$6,13,"") -> 13 | B31: =IF(A31="","",D31*12) -> 120000 | C31: =IF(A31="","",SUM($B$19:B31)) -> 1560000 | D31: =IF(A31="","",$B$4*(1+$B$7)^(13-1)) -> 10000 | E31: =IF(A31="","",E30*(1+$B$15)^12+D31*((1+$B$15)^12-1)/$B$15*(1+$B$15)) -> 3578335.6
A32: =IF(14<=$B$6,14,"") -> 14 | B32: =IF(A32="","",D32*12) -> 120000 | C32: =IF(A32="","",SUM($B$19:B32)) -> 1680000 | D32: =IF(A32="","",$B$4*(1+$B$7)^(14-1)) -> 10000 | E32: =IF(A32="","",E31*(1+$B$15)^12+D32*((1+$B$15)^12-1)/$B$15*(1+$B$15)) -> 4135400.9
A33: =IF(15<=$B$6,15,"") -> 15 | B33: =IF(A33="","",D33*12) -> 120000 | C33: =IF(A33="","",SUM($B$19:B33)) -> 1800000 | D33: =IF(A33="","",$B$4*(1+$B$7)^(15-1)) -> 10000 | E33: =IF(A33="","",E32*(1+$B$15)^12+D33*((1+$B$15)^12-1)/$B$15*(1+$B$15)) -> 4759314
A34: =IF(16<=$B$6,16,"") | B34: =IF(A34="","",D34*12) | C34: =IF(A34="","",SUM($B$19:B34)) | D34: =IF(A34="","",$B$4*(1+$B$7)^(16-1)) | E34: =IF(A34="","",E33*(1+$B$15)^12+D34*((1+$B$15)^12-1)/$B$15*(1+$B$15))
A35: =IF(17<=$B$6,17,"") | B35: =IF(A35="","",D35*12) | C35: =IF(A35="","",SUM($B$19:B35)) | D35: =IF(A35="","",$B$4*(1+$B$7)^(17-1)) | E35: =IF(A35="","",E34*(1+$B$15)^12+D35*((1+$B$15)^12-1)/$B$15*(1+$B$15))
A36: =IF(18<=$B$6,18,"") | B36: =IF(A36="","",D36*12) | C36: =IF(A36="","",SUM($B$19:B36)) | D36: =IF(A36="","",$B$4*(1+$B$7)^(18-1)) | E36: =IF(A36="","",E35*(1+$B$15)^12+D36*((1+$B$15)^12-1)/$B$15*(1+$B$15))
A37: =IF(19<=$B$6,19,"") | B37: =IF(A37="","",D37*12) | C37: =IF(A37="","",SUM($B$19:B37)) | D37: =IF(A37="","",$B$4*(1+$B$7)^(19-1)) | E37: =IF(A37="","",E36*(1+$B$15)^12+D37*((1+$B$15)^12-1)/$B$15*(1+$B$15))
A38: =IF(20<=$B$6,20,"") | B38: =IF(A38="","",D38*12) | C38: =IF(A38="","",SUM($B$19:B38)) | D38: =IF(A38="","",$B$4*(1+$B$7)^(20-1)) | E38: =IF(A38="","",E37*(1+$B$15)^12+D38*((1+$B$15)^12-1)/$B$15*(1+$B$15))
A39: =IF(21<=$B$6,21,"") | B39: =IF(A39="","",D39*12) | C39: =IF(A39="","",SUM($B$19:B39)) | D39: =IF(A39="","",$B$4*(1+$B$7)^(21-1)) | E39: =IF(A39="","",E38*(1+$B$15)^12+D39*((1+$B$15)^12-1)/$B$15*(1+$B$15))
A40: =IF(22<=$B$6,22,"") | B40: =IF(A40="","",D40*12) | C40: =IF(A40="","",SUM($B$19:B40)) | D40: =IF(A40="","",$B$4*(1+$B$7)^(22-1)) | E40: =IF(A40="","",E39*(1+$B$15)^12+D40*((1+$B$15)^12-1)/$B$15*(1+$B$15))
A41: =IF(23<=$B$6,23,"") | B41: =IF(A41="","",D41*12) | C41: =IF(A41="","",SUM($B$19:B41)) | D41: =IF(A41="","",$B$4*(1+$B$7)^(23-1)) | E41: =IF(A41="","",E40*(1+$B$15)^12+D41*((1+$B$15)^12-1)/$B$15*(1+$B$15))
A42: =IF(24<=$B$6,24,"") | B42: =IF(A42="","",D42*12) | C42: =IF(A42="","",SUM($B$19:B42)) | D42: =IF(A42="","",$B$4*(1+$B$7)^(24-1)) | E42: =IF(A42="","",E41*(1+$B$15)^12+D42*((1+$B$15)^12-1)/$B$15*(1+$B$15))
A43: =IF(25<=$B$6,25,"") | B43: =IF(A43="","",D43*12) | C43: =IF(A43="","",SUM($B$19:B43)) | D43: =IF(A43="","",$B$4*(1+$B$7)^(25-1)) | E43: =IF(A43="","",E42*(1+$B$15)^12+D43*((1+$B$15)^12-1)/$B$15*(1+$B$15))
A44: =IF(26<=$B$6,26,"") | B44: =IF(A44="","",D44*12) | C44: =IF(A44="","",SUM($B$19:B44)) | D44: =IF(A44="","",$B$4*(1+$B$7)^(26-1)) | E44: =IF(A44="","",E43*(1+$B$15)^12+D44*((1+$B$15)^12-1)/$B$15*(1+$B$15))
A45: =IF(27<=$B$6,27,"") | B45: =IF(A45="","",D45*12) | C45: =IF(A45="","",SUM($B$19:B45)) | D45: =IF(A45="","",$B$4*(1+$B$7)^(27-1)) | E45: =IF(A45="","",E44*(1+$B$15)^12+D45*((1+$B$15)^12-1)/$B$15*(1+$B$15))
A46: =IF(28<=$B$6,28,"") | B46: =IF(A46="","",D46*12) | C46: =IF(A46="","",SUM($B$19:B46)) | D46: =IF(A46="","",$B$4*(1+$B$7)^(28-1)) | E46: =IF(A46="","",E45*(1+$B$15)^12+D46*((1+$B$15)^12-1)/$B$15*(1+$B$15))
A47: =IF(29<=$B$6,29,"") | B47: =IF(A47="","",D47*12) | C47: =IF(A47="","",SUM($B$19:B47)) | D47: =IF(A47="","",$B$4*(1+$B$7)^(29-1)) | E47: =IF(A47="","",E46*(1+$B$15)^12+D47*((1+$B$15)^12-1)/$B$15*(1+$B$15))
A48: =IF(30<=$B$6,30,"") | B48: =IF(A48="","",D48*12) | C48: =IF(A48="","",SUM($B$19:B48)) | D48: =IF(A48="","",$B$4*(1+$B$7)^(30-1)) | E48: =IF(A48="","",E47*(1+$B$15)^12+D48*((1+$B$15)^12-1)/$B$15*(1+$B$15))
A50: Assumption: expected return is user-entered (default 12% p.a. is illustrative, not guaranteed). Mutual fund returns are subject to market risk.

Sheet Savings Comparison
A1: Where does ₹1,00,000 grow more? (5-year comparison)
A2: Rates are illustrative inputs - replace with current rates from the bank's website.
A4: Amount invested | B4: 100000
A5: Years | B5: 5
A7: Option | B7: Annual rate | C7: Compounding per year | D7: Maturity value | E7: Gain
A8: Savings account (illustrative) | B8: 0.03 | C8: 4 | D8: =$B$4*(1+B8/C8)^(C8*$B$5) -> 116118.41 | E8: =D8-$B$4 -> 16118.414
A9: Fixed deposit (illustrative) | B9: 0.07 | C9: 4 | D9: =$B$4*(1+B9/C9)^(C9*$B$5) -> 141477.82 | E9: =D9-$B$4 -> 41477.82
A10: Debt mutual fund (illustrative) | B10: 0.075 | C10: 1 | D10: =$B$4*(1+B10/C10)^(C10*$B$5) -> 143562.93 | E10: =D10-$B$4 -> 43562.933
A11: Equity mutual fund (illustrative) | B11: 0.12 | C11: 1 | D11: =$B$4*(1+B11/C11)^(C11*$B$5) -> 176234.17 | E11: =D11-$B$4 -> 76234.168
A13: Equity returns are not assured and carry market risk. For learning purposes only.
